8259A Programmable Interrupt Controller Project/Workspace/PIC_tb/IRR_tb/InterruptRequestRegister.v
module InterruptRequestRegister (
    input [7:0] IR0_to_IR7,            // Input: Interrupt requests from IR0 to IR7.
    input [7:0] bitToMask,             // Input: Masking bits from IMR for corresponding IRs.
    input readPriority,                // Input: Read priority signal from control logic.
    input readIRR,                     // Input: Signal to output IRR values to data buffer.
    input [2:0] resetIRR,              // Input: Signal from priority resolver to reset serviced interrupts.
    input [7:0] ICW1,                  // Input: Initialization Command Word 1 with LTIM bit.

    output reg [7:0] risedBits = 8'b0, // Output: Rised bits indicating valid interrupts.
    output reg [7:0] dataBuffer,       // Output: Buffer for interrupts reset by resetIRR.
    output reg readPriorityAck = 1'b0 // Output: Acknowledge signal for readPriority.
);

    // Internal register to hold the current state of interrupts
    reg [7:0] interruptState;

    // Determine operating mode based on ICW1's LTIM bit
    reg levelTriggered;
    
    // Logic to handle valid interrupts and reset based on readPriority and resetIRR signals
    // For edge-triggered interrupts
    always @(posedge IR0_to_IR7, bitToMask) begin
	levelTriggered = ICW1[3];
        if (!levelTriggered) begin
            // Combine interrupt requests with mask bits to find valid interrupts
            // Valid interrupts have a '0' in bitToMask corresponding to '1' in IR signals
            interruptState = IR0_to_IR7 & ~bitToMask;
        end
    end

    // For level-triggered interrupts
    always @(IR0_to_IR7, bitToMask) begin
	levelTriggered = ICW1[3];
        if (levelTriggered) begin
            // Combine interrupt requests with mask bits to find valid interrupts
            // Valid interrupts have a '0' in bitToMask corresponding to '1' in IR signals
            interruptState = IR0_to_IR7 & ~bitToMask;
        end
    end

    // Logic to handle resetting interrupts based on readPriority and resetIRR signals
    always @(posedge readPriority) begin
        // Reset corresponding interrupts in IRR based on priority resolution and resetIRR value
        if (resetIRR != 0) begin
            interruptState = interruptState & ~(1 << resetIRR);
        end else begin
            interruptState[0] = 0; // Reset IR0 when resetIRR is '0'
        end
        // Toggle readPriorityAck to indicate acknowledgment
        readPriorityAck <= ~readPriorityAck;
    end

    // Storing interrupts in dataBuffer when readIRR is asserted
    always @* begin
        if (readIRR) begin
            dataBuffer = interruptState;
        end else begin
            dataBuffer = 8'bZ; // Output high-impedance state when readIRR is inactive
        end
    end

    // Output the detected active interrupts in risedBits
    always @(*) begin
        risedBits = interruptState;
    end

endmodule

8259A Programmable Interrupt Controller Project/Workspace/PIC_tb/IRR_tb/InterruptRequestRegister_tb.v
/**
 * @file irr_tb.v
 * @brief Testbench for the Interrupt Request Register (IRR) module
 */

//`timescale 1ns/1ps // Define timescale for simulation accuracy

/**
 * @brief Testbench for the Interrupt Request Register (IRR) module
 * @details Simulates various scenarios to verify the functionality of the InterruptRequestRegister module.
 */
module InterruptRequestRegister_tb;

    // Inputs
    reg [7:0] IR0_to_IR7;      // Input: Interrupt requests from IR0 to IR7.
    reg [7:0] bitToMask;       // Input: Masking bits from IMR for corresponding IRs.
    reg readPriority;          // Input: Read priority signal from control logic.
    reg readIRR;               // Input: Signal to output IRR values to data buffer.
    reg [2:0] resetIRR;        // Input: Signal from priority resolver to reset serviced interrupts.
    reg [7:0] ICW1;            // Input: For Initialization Command Word 1

    
    // Outputs
    wire [7:0] risedBits;      // Output: Rised bits indicating valid interrupts.
    wire [7:0] dataBuffer;     // Output: Buffer for interrupts reset by resetIRR.
    wire readPriorityAck;
    

    // Instantiate the InterruptRequestRegister module
    InterruptRequestRegister irr_inst (
        .IR0_to_IR7(IR0_to_IR7),
        .bitToMask(bitToMask),    
        .readPriority(readPriority),
        .readIRR(readIRR),
        .resetIRR(resetIRR),
        .ICW1(ICW1),
        .risedBits(risedBits),
        .dataBuffer(dataBuffer),
        .readPriorityAck(readPriorityAck)
    );

    integer num_random_test_cases = 10;
    integer i;

    // Stimulus
    initial begin
        $dumpfile("irr_tb.vcd"); // Define output VCD file
        $dumpvars(0, InterruptRequestRegister_tb); // Dump variables for simulation

        // Test case 1: No interrupts, all masked
        i = 0;
        IR0_to_IR7 = $urandom; // Generate random value for IR0_to_IR7
        bitToMask = $urandom; // Generate random value for bitToMask
        readPriority = $urandom_range(0, 1); // Random value for readPriority
        readIRR = $urandom_range(0, 1); // Random value for readIRR
        resetIRR = $urandom_range(0, 7); // Random value for resetIRR
        ICW1 = $urandom; // Randomize ICW1
        #10;// Delay to observe the behavior

        // Test case 2: Simulate interrupts and mask conditions
        i = 1;
        IR0_to_IR7 = $urandom; // Generate random value for IR0_to_IR7
        bitToMask = $urandom; // Generate random value for bitToMask
        readPriority = $urandom_range(0, 1); // Random value for readPriority
        readIRR = $urandom_range(0, 1); // Random value for readIRR
        resetIRR = $urandom_range(0, 7); // Random value for resetIRR
        ICW1 = $urandom; // Randomize ICW1
        #10;// Delay to observe the behavior

        // Test case 3: Testing the behavior when readPriority is set and resetIRR is applied
        i = 2; // Set test case number
        IR0_to_IR7 = 8'b01101010; // Simulate specific interrupt requests
        bitToMask = 8'b10110100; // Mask certain interrupts
        readIRR = $urandom_range(0, 1); // Randomize readIRR
        resetIRR = 6; // Apply reset to a specific interrupt
        ICW1 = 8'b00001000; // Set LTIM bit to 1 or 0 according to requirements
        #5 readPriority = 1'b1; // Activate read priority
        #10; // Delay to observe the behavior

        for (i = 3; i < num_random_test_cases; i = i + 1) begin
            // Generate random values for inputs
            IR0_to_IR7 = $urandom; // Random value for IR0_to_IR7
            bitToMask = $urandom; // Random value for bitToMask
            readPriority = $urandom_range(0, 1); // Random value for readPriority
            readIRR = $urandom_range(0, 1); // Random value for readIRR
            resetIRR = $urandom_range(0, 7); // Random value for resetIRR
            ICW1 = $urandom; // Randomize ICW1
            #10; // Add delay for each test case
        end

        $finish; // End simulation
    end

    always @(readPriorityAck) begin
        readPriority = 0;
    end

endmodule

8259A Programmable Interrupt Controller Project/Workspace/PIC_tb/IRR_tb/irr_tb.vcd
$date
	Tue Dec 26 01:08:48 2023
$end
$version
	ModelSim Version 10.5b
$end
$timescale
	1ps
$end

$scope module InterruptRequestRegister_tb $end
$var reg 8 ! IR0_to_IR7 [7:0] $end
$var reg 8 " bitToMask [7:0] $end
$var reg 1 # readPriority $end
$var reg 1 $ readIRR $end
$var reg 3 % resetIRR [2:0] $end
$var reg 8 & ICW1 [7:0] $end
$var wire 1 ' risedBits [7] $end
$var wire 1 ( risedBits [6] $end
$var wire 1 ) risedBits [5] $end
$var wire 1 * risedBits [4] $end
$var wire 1 + risedBits [3] $end
$var wire 1 , risedBits [2] $end
$var wire 1 - risedBits [1] $end
$var wire 1 . risedBits [0] $end
$var wire 1 / dataBuffer [7] $end
$var wire 1 0 dataBuffer [6] $end
$var wire 1 1 dataBuffer [5] $end
$var wire 1 2 dataBuffer [4] $end
$var wire 1 3 dataBuffer [3] $end
$var wire 1 4 dataBuffer [2] $end
$var wire 1 5 dataBuffer [1] $end
$var wire 1 6 dataBuffer [0] $end
$var wire 1 7 readPriorityAck $end
$var integer 32 8 num_random_test_cases $end
$var integer 32 9 i $end

$scope module irr_inst $end
$var wire 1 : IR0_to_IR7 [7] $end
$var wire 1 ; IR0_to_IR7 [6] $end
$var wire 1 < IR0_to_IR7 [5] $end
$var wire 1 = IR0_to_IR7 [4] $end
$var wire 1 > IR0_to_IR7 [3] $end
$var wire 1 ? IR0_to_IR7 [2] $end
$var wire 1 @ IR0_to_IR7 [1] $end
$var wire 1 A IR0_to_IR7 [0] $end
$var wire 1 B bitToMask [7] $end
$var wire 1 C bitToMask [6] $end
$var wire 1 D bitToMask [5] $end
$var wire 1 E bitToMask [4] $end
$var wire 1 F bitToMask [3] $end
$var wire 1 G bitToMask [2] $end
$var wire 1 H bitToMask [1] $end
$var wire 1 I bitToMask [0] $end
$var wire 1 J readPriority $end
$var wire 1 K readIRR $end
$var wire 1 L resetIRR [2] $end
$var wire 1 M resetIRR [1] $end
$var wire 1 N resetIRR [0] $end
$var wire 1 O ICW1 [7] $end
$var wire 1 P ICW1 [6] $end
$var wire 1 Q ICW1 [5] $end
$var wire 1 R ICW1 [4] $end
$var wire 1 S ICW1 [3] $end
$var wire 1 T ICW1 [2] $end
$var wire 1 U ICW1 [1] $end
$var wire 1 V ICW1 [0] $end
$var reg 8 W risedBits [7:0] $end
$var reg 8 X dataBuffer [7:0] $end
$var reg 1 Y readPriorityAck $end
$var reg 8 Z interruptState [7:0] $end
$var reg 1 [ levelTriggered $end
$upscope $end
$upscope $end
$enddefinitions $end
#0
$dumpvars
b10111000 !
b100110 "
0#
0$
b110 %
b1000110 &
b10011000 W
bz X
0Y
b10011000 Z
0[
b1010 8
b0 9
0.
0-
0,
1+
1*
0)
0(
1'
z6
z5
z4
z3
z2
z1
z0
z/
07
0V
1U
1T
0S
0R
0Q
1P
0O
0N
1M
1L
0K
0J
0I
1H
1G
0F
0E
1D
0C
0B
0A
0@
0?
1>
1=
1<
0;
1:
$end
#10
b1 9
b1110010 !
b101110 "
1#
b10 %
b10110100 &
0U
1R
1Q
0P
1O
0L
1F
1@
0>
1;
0:
1J
b1010000 Z
b1010000 W
0+
1(
0'
1Y
17
#20
b10 9
b1101010 !
b10110100 "
1$
b110 %
b1000 &
0T
1S
0R
0Q
0O
1L
0H
0F
1E
1B
1>
0=
1K
b1010000 X
1[
b1001010 Z
06
05
04
03
12
01
10
0/
b1001010 X
b1001010 W
1-
1+
0*
15
13
02
#35
b11 9
b1010110 !
b110101 "
0#
0$
b101 %
b11011011 &
1V
1U
1R
1P
1O
1N
0M
1I
0B
1?
0>
1=
0<
0J
0K
bz X
b1000010 Z
z6
z5
z4
z3
z2
z1
z0
z/
b1000010 W
0+
#45
b100 9
b101 !
b11100011 "
1$
b100101 &
0U
1T
0S
0R
1Q
0P
0O
1H
0G
0E
1C
1B
1A
0@
0=
0;
1K
b1000010 X
0[
b100 Z
06
15
04
03
02
01
10
0/
b100 X
b100 W
0-
1,
0(
05
14
00
#55
b101 9
b11101001 !
b1011101 "
0$
b11 %
b1010110 &
0V
1U
1R
0Q
1P
1M
0L
0H
1G
1F
1E
0D
0B
0?
1>
1<
1;
1:
0K
bz X
b10100000 Z
z6
z5
z4
z3
z2
z1
z0
z/
b10100000 W
0,
1)
1'
#65
b110 9
b11001001 !
b10111001 "
b110 %
b11010100 &
0U
1O
0N
1L
0G
1D
0C
1B
0<
b1000000 Z
b1000000 W
0)
1(
0'
#75
b111 9
b10001110 !
b11000000 "
1#
1$
b111 %
b1011000 &
0T
1S
0O
1N
0I
0F
0E
0D
1C
0A
1@
1?
0;
1J
1K
b1000000 X
1[
b1110 Z
06
05
04
03
02
01
10
0/
b1110 X
b1110 W
1-
1,
1+
0(
15
14
13
00
0Y
07
#85
b1000 9
b1010001 !
b110010 "
0$
b11 %
b1011010 &
1U
0L
1H
1E
1D
0C
0B
1A
0@
0?
0>
1=
1;
0:
0K
bz X
b1000001 Z
z6
z5
z4
z3
z2
z1
z0
z/
b1000001 W
1.
0-
0,
0+
1(
#95
b1001 9
b11100110 !
b11110110 "
b111 %
b11101111 &
1V
1T
0R
1Q
1O
1L
1G
1C
1B
0A
1@
1?
0=
1<
1:
b0 Z
b0 W
0.
0(
