8259A Programmable Interrupt Controller Project/Workspace/PIC_tb/IRR_tb/InterruptRequestRegister.v
/**
 * @file irr.v
 * @brief Interrupt Request Register (IRR) module for interrupt handling
 */

/**
 * @brief Interrupt Request Register (IRR) Module
 * @details Manages the Interrupt Request Register to handle interrupt requests and priority resolution.
 * It interfaces with the Interrupt Mask Register (IMR) and control logic for interrupt servicing.
 */
module InterruptRequestRegister (
    input [7:0] IR0_to_IR7,            // Input: Interrupt requests from IR0 to IR7.
    input [7:0] bitToMask,             // Input: Masking bits from IMR for corresponding IRs.
    input readPriority,                // Input: Read priority signal from control logic.
    input readIRR,                     // Input: Signal to output IRR values to data buffer.
    input [2:0] resetIRR,              // Input: Signal from priority resolver to reset serviced interrupts.
    input [7:0] ICW1,                  // Input: Initialization Command Word 1 with LTIM bit.
    output reg [7:0] risedBits = 8'b0, // Output: Rised bits indicating valid interrupts.
    output reg [7:0] dataBuffer        // Output: Buffer for interrupts reset by resetIRR.
);

    // Internal register to hold the current state of interrupts
    reg [7:0] interruptState;

    // Determine operating mode based on ICW1's LTIM bit
    reg levelTriggered;

/*     // Logic to handle valid interrupts and reset based on readPriority and resetIRR signals
    always @(*) begin
        // Combine interrupt requests with mask bits to find valid interrupts
        // Valid interrupts have a '0' in bitToMask corresponding to '1' in IR signals
        interruptState = IR0_to_IR7 & ~bitToMask;

        // Resetting interrupts based on readPriority and resetIRR signals
        if (readPriority) begin
            // Reset corresponding interrupts in IRR based on priority resolution and resetIRR value
            if (resetIRR != 0) begin
                interruptState = interruptState & ~(1 << resetIRR);
            end else begin
                interruptState[0] = 0; // Reset IR0 when resetIRR is '0'
            end

            irrReadPriorityACK = ~ irrReadPriorityACK;

        end
    end */
    //update start "By eslam"
    always @(IR0_to_IR7, bitToMask) begin
        // Combine interrupt requests with mask bits to find valid interrupts
        // Valid interrupts have a '0' in bitToMask corresponding to '1' in IR signals
        interruptState = IR0_to_IR7 & ~bitToMask;
    end

    always @(posedge readPriority) begin
        // Resetting interrupts based on readPriority and resetIRR signals
        // Reset corresponding interrupts in IRR based on priority resolution and resetIRR value
        if (resetIRR != 0) begin
            interruptState = interruptState & ~(1 << resetIRR);
        end else begin
            interruptState[0] = 0; // Reset IR0 when resetIRR is '0'
        end
        readPriorityAck <= ~readPriorityAck;
    end
    //end update start "By eslam"


    // Storing interrupts in dataBuffer when readIRR is asserted
    always @(*) begin
        if (readIRR) begin
            dataBuffer = interruptState;
        end else begin
            dataBuffer = 8'bZ;
        end
    end

    // Update risedBits based on level/edge triggered interrupt mode
    always @(*) begin
        // Assuming LTIM bit is at position 3 in ICW1
        levelTriggered = ICW1[3]; // LTIM bit determines the mode

        // If LTIM = 1, then operate in level interrupt mode.
        // If LTIM = 0, then operate in edge interrupt mode.
        if (levelTriggered == 1) begin
            // Level-triggered mode: The interrupt is considered asserted as long as the signal remains in that state.
            risedBits = interruptState;
        end else begin
            // Edge-triggered mode: The interrupt is signaled at the moment of the transition (rising or falling edge) of the signal.
            // Detect the rising edge to signal the interrupt
            risedBits = interruptState & ~risedBits;
        end
    end

endmodule

8259A Programmable Interrupt Controller Project/Workspace/PIC_tb/IRR_tb/InterruptRequestRegister_tb.v
/**
 * @file irr_tb.v
 * @brief Testbench for the Interrupt Request Register (IRR) module
 */

//`timescale 1ns/1ps // Define timescale for simulation accuracy

/**
 * @brief Testbench for the Interrupt Request Register (IRR) module
 * @details Simulates various scenarios to verify the functionality of the InterruptRequestRegister module.
 */
module InterruptRequestRegister_tb;

    // Inputs
    reg [7:0] IR0_to_IR7;      // Input: Interrupt requests from IR0 to IR7.
    reg [7:0] bitToMask;       // Input: Masking bits from IMR for corresponding IRs.
    reg readPriority;          // Input: Read priority signal from control logic.
    reg readIRR;               // Input: Signal to output IRR values to data buffer.
    reg [2:0] resetIRR;        // Input: Signal from priority resolver to reset serviced interrupts.
    reg [7:0] ICW1;            // Input: For Initialization Command Word 1

    
    // Outputs
    wire [7:0] risedBits;      // Output: Rised bits indicating valid interrupts.
    wire [7:0] dataBuffer;     // Output: Buffer for interrupts reset by resetIRR.
    

    // Instantiate the InterruptRequestRegister module
    InterruptRequestRegister irr_inst (
        .IR0_to_IR7(IR0_to_IR7),
        .bitToMask(bitToMask),    
        .readPriority(readPriority),
        .readIRR(readIRR),
        .resetIRR(resetIRR),
        .ICW1(ICW1),
        .risedBits(risedBits),
        .dataBuffer(dataBuffer)
    );

    integer num_random_test_cases = 10;
    integer i;

    // Stimulus
    initial begin
        $dumpfile("irr_tb.vcd"); // Define output VCD file
        $dumpvars(0, InterruptRequestRegister_tb); // Dump variables for simulation

        // Test case 1: No interrupts, all masked
        i = 0;
        IR0_to_IR7 = $urandom; // Generate random value for IR0_to_IR7
        bitToMask = $urandom; // Generate random value for bitToMask
        readPriority = $urandom_range(0, 1); // Random value for readPriority
        readIRR = $urandom_range(0, 1); // Random value for readIRR
        resetIRR = $urandom_range(0, 7); // Random value for resetIRR
        ICW1 = $urandom; // Randomize ICW1
        #10;// Delay to observe the behavior

        // Test case 2: Simulate interrupts and mask conditions
        i = 1;
        IR0_to_IR7 = $urandom; // Generate random value for IR0_to_IR7
        bitToMask = $urandom; // Generate random value for bitToMask
        readPriority = $urandom_range(0, 1); // Random value for readPriority
        readIRR = $urandom_range(0, 1); // Random value for readIRR
        resetIRR = $urandom_range(0, 7); // Random value for resetIRR
        ICW1 = $urandom; // Randomize ICW1
        #10;// Delay to observe the behavior

        // Test case 3: Testing the behavior when readPriority is set and resetIRR is applied
        i = 2; // Set test case number
        IR0_to_IR7 = 8'b01101010; // Simulate specific interrupt requests
        bitToMask = 8'b10110100; // Mask certain interrupts
        readPriority = 1'b1; // Activate read priority
        readIRR = $urandom_range(0, 1); // Randomize readIRR
        resetIRR = 6; // Apply reset to a specific interrupt
        ICW1 = 8'b00001000; // Set LTIM bit to 1 or 0 according to requirements
        #5 readPriority = 1'b1; // Activate read priority
        #10; // Delay to observe the behavior

        for (i = 3; i < num_random_test_cases; i = i + 1) begin
            // Generate random values for inputs
            IR0_to_IR7 = $urandom; // Random value for IR0_to_IR7
            bitToMask = $urandom; // Random value for bitToMask
            readPriority = $urandom_range(0, 1); // Random value for readPriority
            readIRR = $urandom_range(0, 1); // Random value for readIRR
            resetIRR = $urandom_range(0, 7); // Random value for resetIRR
            ICW1 = $urandom; // Randomize ICW1
            #10; // Add delay for each test case
        end

        $finish; // End simulation
    end

endmodule

8259A Programmable Interrupt Controller Project/Workspace/PIC_tb/IRR_tb/irr_tb.vcd
$date
	Thu Dec 21 18:29:16 2023
$end
$version
	ModelSim Version 10.5b
$end
$timescale
	1ps
$end

$scope module InterruptRequestRegister_tb $end
$var reg 8 ! IR0_to_IR7 [7:0] $end
$var reg 8 " bitToMask [7:0] $end
$var reg 1 # readPriority $end
$var reg 1 $ readIRR $end
$var reg 3 % resetIRR [2:0] $end
$var reg 8 & ICW1 [7:0] $end
$var wire 1 ' risedBits [7] $end
$var wire 1 ( risedBits [6] $end
$var wire 1 ) risedBits [5] $end
$var wire 1 * risedBits [4] $end
$var wire 1 + risedBits [3] $end
$var wire 1 , risedBits [2] $end
$var wire 1 - risedBits [1] $end
$var wire 1 . risedBits [0] $end
$var wire 1 / dataBuffer [7] $end
$var wire 1 0 dataBuffer [6] $end
$var wire 1 1 dataBuffer [5] $end
$var wire 1 2 dataBuffer [4] $end
$var wire 1 3 dataBuffer [3] $end
$var wire 1 4 dataBuffer [2] $end
$var wire 1 5 dataBuffer [1] $end
$var wire 1 6 dataBuffer [0] $end
$var integer 32 7 num_random_test_cases $end
$var integer 32 8 i $end

$scope module irr_inst $end
$var wire 1 9 IR0_to_IR7 [7] $end
$var wire 1 : IR0_to_IR7 [6] $end
$var wire 1 ; IR0_to_IR7 [5] $end
$var wire 1 < IR0_to_IR7 [4] $end
$var wire 1 = IR0_to_IR7 [3] $end
$var wire 1 > IR0_to_IR7 [2] $end
$var wire 1 ? IR0_to_IR7 [1] $end
$var wire 1 @ IR0_to_IR7 [0] $end
$var wire 1 A bitToMask [7] $end
$var wire 1 B bitToMask [6] $end
$var wire 1 C bitToMask [5] $end
$var wire 1 D bitToMask [4] $end
$var wire 1 E bitToMask [3] $end
$var wire 1 F bitToMask [2] $end
$var wire 1 G bitToMask [1] $end
$var wire 1 H bitToMask [0] $end
$var wire 1 I readPriority $end
$var wire 1 J readIRR $end
$var wire 1 K resetIRR [2] $end
$var wire 1 L resetIRR [1] $end
$var wire 1 M resetIRR [0] $end
$var wire 1 N ICW1 [7] $end
$var wire 1 O ICW1 [6] $end
$var wire 1 P ICW1 [5] $end
$var wire 1 Q ICW1 [4] $end
$var wire 1 R ICW1 [3] $end
$var wire 1 S ICW1 [2] $end
$var wire 1 T ICW1 [1] $end
$var wire 1 U ICW1 [0] $end
$var reg 8 V risedBits [7:0] $end
$var reg 8 W dataBuffer [7:0] $end
$var reg 8 X interruptState [7:0] $end
$var reg 1 Y levelTriggered $end
$upscope $end
$upscope $end
$enddefinitions $end
#0
$dumpvars
b10111000 !
b100110 "
0#
0$
b110 %
b1000110 &
b10011000 V
bz W
b10011000 X
0Y
b1010 7
b0 8
0.
0-
0,
1+
1*
0)
0(
1'
z6
z5
z4
z3
z2
z1
z0
z/
0U
1T
1S
0R
0Q
0P
1O
0N
0M
1L
1K
0J
0I
0H
1G
1F
0E
0D
1C
0B
0A
0@
0?
0>
1=
1<
1;
0:
19
$end
#10
b1 8
b1110010 !
b101110 "
1#
b10 %
b10110100 &
1I
0T
1Q
1P
0O
1N
0K
1E
1?
0=
1:
09
b0 V
b1010000 X
0+
0*
0'
b1010000 V
1*
1(
#20
b10 8
b1101010 !
b10110100 "
1$
b110 %
b1000 &
1J
0S
1R
0Q
0P
0N
1K
0G
0E
1D
1A
1=
0<
b1001010 X
b1010 X
1Y
b1010 V
b1010 W
06
15
04
13
02
01
00
0/
1-
1+
0*
0(
#30
b11 8
b1010110 !
b110101 "
0#
0$
b101 %
b11011011 &
0I
0J
1U
1T
1Q
1O
1N
1M
0L
1H
0A
1>
0=
1<
0;
bz W
b1000010 X
z6
z5
z4
z3
z2
z1
z0
z/
b1000010 V
0+
1(
#40
b100 8
b101 !
b11100011 "
1$
b100101 &
1J
0T
1S
0R
0Q
1P
0O
0N
1G
0F
0D
1B
1A
1@
0?
0<
0:
b100 X
0Y
b100 V
b100 W
06
05
14
03
02
01
00
0/
0-
1,
0(
#50
b101 8
b11101001 !
b1011101 "
0$
b11 %
b1010110 &
0J
0U
1T
1Q
0P
1O
1L
0K
0G
1F
1E
1D
0C
0A
0>
1=
1;
1:
19
b10100000 X
b10100000 V
bz W
z6
z5
z4
z3
z2
z1
z0
z/
0,
1)
1'
#60
b110 8
b11001001 !
b10111001 "
b110 %
b11010100 &
0T
1N
0M
1K
0F
1C
0B
1A
0;
b1000000 X
b1000000 V
0)
1(
0'
#70
b111 8
b10001110 !
b11000000 "
1#
1$
b111 %
b1011000 &
1I
1J
0S
1R
0N
1M
0H
0E
0D
0C
1B
0@
1?
1>
0:
1Y
b1000000 W
b1110 X
06
05
04
03
02
01
10
0/
b1110 V
b1110 W
15
14
13
00
1-
1,
1+
0(
#80
b1000 8
b1010001 !
b110010 "
0$
b11 %
b1011010 &
0J
1T
0K
1G
1D
1C
0B
0A
1@
0?
0>
0=
1<
1:
09
b1000001 X
b1000001 V
bz W
z6
z5
z4
z3
z2
z1
z0
z/
1.
0-
0,
0+
1(
#90
b1001 8
b11100110 !
b11110110 "
b111 %
b11101111 &
1U
1S
0Q
1P
1N
1K
1F
1B
1A
0@
1?
1>
0<
1;
19
b0 X
b0 V
0.
0(
#100
b1010 8
